truelink/__init__.py
truelink/core.py
truelink/exceptions.py
truelink/mimetypes.py
truelink/types.py
truelink/resolvers/__init__.py
truelink/resolvers/base.py
truelink/resolvers/buzzheavier.py
truelink/resolvers/fichier.py
truelink/resolvers/fuckingfast.py
truelink/resolvers/gofile.py
truelink/resolvers/linkbox.py
truelink/resolvers/linkvertise.py
truelink/resolvers/lulacloud.py
truelink/resolvers/mediafile.py
truelink/resolvers/mediafire.py
truelink/resolvers/onedrive.py
truelink/resolvers/pcloud.py
truelink/resolvers/pixeldrain.py
truelink/resolvers/ranoz.py
truelink/resolvers/spankbang.py
truelink/resolvers/streamtape.py
truelink/resolvers/swisstransfer.py
truelink/resolvers/terabox.py
truelink/resolvers/tmpsend.py
truelink/resolvers/uploadee.py
truelink/resolvers/xfeed.py
truelink/resolvers/xham.py
truelink/resolvers/yandexdisk.py
truelink-1.4.8.dist-info/METADATA
truelink-1.4.8.dist-info/WHEEL
truelink-1.4.8.dist-info/licenses/LICENSE
truelink-1.4.8.dist-info/licenses/NOTICE
truelink-1.4.8.dist-info/RECORD
